espark_core-0.5.10.dist-info/licenses/LICENSE
esparkcore/__init__.py
esparkcore/constants.py
esparkcore/data/__init__.py
esparkcore/data/database.py
esparkcore/data/models/__init__.py
esparkcore/data/models/device.py
esparkcore/data/models/notification.py
esparkcore/data/models/outbox.py
esparkcore/data/models/telemetry.py
esparkcore/data/models/trigger.py
esparkcore/data/models/version.py
esparkcore/data/repositories/__init__.py
esparkcore/data/repositories/base_repository.py
esparkcore/data/repositories/device_repository.py
esparkcore/data/repositories/notification_repository.py
esparkcore/data/repositories/outbox_repository.py
esparkcore/data/repositories/telemetry_repository.py
esparkcore/data/repositories/trigger_repository.py
esparkcore/data/repositories/version_repository.py
esparkcore/notifications/__init__.py
esparkcore/notifications/notifier.py
esparkcore/notifications/slack_notifier.py
esparkcore/routers/__init__.py
esparkcore/routers/base_router.py
esparkcore/routers/device_router.py
esparkcore/routers/notification_router.py
esparkcore/routers/telemetry_router.py
esparkcore/routers/trigger_router.py
esparkcore/routers/version_router.py
esparkcore/schedules/__init__.py
esparkcore/schedules/outbox.py
esparkcore/schedules/scheduler.py
esparkcore/services/__init__.py
esparkcore/services/mqtt.py
esparkcore/utils/__init__.py
esparkcore/utils/logging.py
espark_core-0.5.10.dist-info/METADATA
espark_core-0.5.10.dist-info/WHEEL
espark_core-0.5.10.dist-info/top_level.txt
espark_core-0.5.10.dist-info/RECORD
