Metadata-Version: 2.4
Name: espark-core
Version: 0.5.10
Summary: The core module of the Espark ESP32-based IoT device management framework.
License: MIT
Requires-Python: >=3.10
License-File: LICENSE
Requires-Dist: aiomqtt>=2.5.0
Requires-Dist: apscheduler>=3.11.2
Requires-Dist: fastapi>=0.128.0
Requires-Dist: packaging>=25.0
Requires-Dist: slack-sdk==3.39.0
Requires-Dist: sqlalchemy>=2.0.45
Requires-Dist: sqlmodel>=0.0.31
Requires-Dist: uvicorn[standard]>=0.40.0
Provides-Extra: dev
Requires-Dist: aiosqlite==0.22.1; extra == "dev"
Requires-Dist: autopep8==2.3.2; extra == "dev"
Requires-Dist: build==1.3.0; extra == "dev"
Requires-Dist: fastapi-cli[standard-no-fastapi-cloud-cli]==0.0.20; extra == "dev"
Requires-Dist: httpx==0.28.1; extra == "dev"
Requires-Dist: pycodestyle==2.14.0; extra == "dev"
Requires-Dist: pylint==4.0.4; extra == "dev"
Requires-Dist: pytest==9.0.2; extra == "dev"
Requires-Dist: pytest-asyncio==1.3.0; extra == "dev"
Requires-Dist: pytest-cov==7.0.0; extra == "dev"
Requires-Dist: twine==6.2.0; extra == "dev"
Dynamic: description
Dynamic: description-content-type
Dynamic: license
Dynamic: license-file
Dynamic: provides-extra
Dynamic: requires-dist
Dynamic: requires-python
Dynamic: summary
